kaititu-1.0.2.dist-info/METADATA
kaititu-1.0.2.dist-info/WHEEL
kaititu-1.0.2.dist-info/entry_points.txt
kaititu-1.0.2.dist-info/licenses/LICENSE
kaititu/__init__.py
kaititu/audit/__init__.py
kaititu/audit/mssql.py
kaititu/audit/mysql.py
kaititu/audit/oracle.py
kaititu/audit/postgres.py
kaititu-1.0.2.dist-info/RECORD
