Metadata-Version: 2.1
Name: kaititu
Version: 1.0.2
Summary: It is a library to deal with operational and analytical tasks on popular database management system.
Author-Email: "Kelvin S. Amorim" <kelvin.amorim@silverlayer.space>
License: Apache License
Classifier: Development Status :: 4 - Beta
Classifier: License :: OSI Approved :: Apache Software License
Classifier: Intended Audience :: Developers
Classifier: Operating System :: OS Independent
Classifier: Programming Language :: Python :: 3
Classifier: Programming Language :: Python :: 3.10
Classifier: Programming Language :: Python :: 3.11
Classifier: Programming Language :: Python :: 3.12
Classifier: Programming Language :: Python :: 3.13
Classifier: Topic :: Database
Project-URL: Repository, https://github.com/silverlayer/kaititu.git
Project-URL: Documentation, https://silverlayer.github.io/kaititu
Project-URL: Issues, https://github.com/silverlayer/kaititu/issues
Requires-Python: >=3.10
Requires-Dist: polars<2.0.0,>=1.24.0
Requires-Dist: sqlalchemy<3.0.0,>=2.0.38
Requires-Dist: pyodbc<6.0.0,>=5.2.0
Requires-Dist: psycopg2<3.0.0,>=2.9.10
Requires-Dist: mysqlclient<3.0.0,>=2.2.7
Requires-Dist: oracledb<3.0.0,>=2.5.1
